DeepStorm/VERSION
DeepStorm/__init__.py
DeepStorm/logger.py
DeepStorm/model.py
DeepStorm/Activations/__init__.py
DeepStorm/Activations/relu.py
DeepStorm/Activations/sigmoid.py
DeepStorm/Activations/softmax.py
DeepStorm/Initializers/__init__.py
DeepStorm/Initializers/constant.py
DeepStorm/Initializers/he.py
DeepStorm/Initializers/uniform_random.py
DeepStorm/Initializers/xavier.py
DeepStorm/Layers/__init__.py
DeepStorm/Layers/base.py
DeepStorm/Layers/batch_normalization.py
DeepStorm/Layers/conv.py
DeepStorm/Layers/dropout.py
DeepStorm/Layers/flatten.py
DeepStorm/Layers/linear.py
DeepStorm/Layers/pooling.py
DeepStorm/Losses/__init__.py
DeepStorm/Losses/cross_entropy.py
DeepStorm/Losses/l2.py
DeepStorm/Optimizers/__init__.py
DeepStorm/Optimizers/adam.py
DeepStorm/Optimizers/sgd.py
DeepStorm-1.1.0.dist-info/LICENSE
DeepStorm-1.1.0.dist-info/METADATA
DeepStorm-1.1.0.dist-info/WHEEL
DeepStorm-1.1.0.dist-info/top_level.txt
DeepStorm-1.1.0.dist-info/RECORD
