Metadata-Version: 2.1
Name: DeepStorm
Version: 1.1.0
Summary: Deep Learning framework from scratch
Home-page: https://github.com/HassanRady/DeepStorm
Author: Hassan Rady
Author-email: hassan.khaled.rady@gmail.com
License: MIT license
Keywords: Tweets
Classifier: Development Status :: 2 - Pre-Alpha
Classifier: Intended Audience :: Developers
Classifier: License :: OSI Approved :: MIT License
Classifier: Natural Language :: English
Classifier: Programming Language :: Python :: 3
Classifier: Programming Language :: Python :: 3.6
Classifier: Programming Language :: Python :: 3.7
Classifier: Programming Language :: Python :: 3.8
Requires-Python: ==3.9.16
License-File: LICENSE
Requires-Dist: scikit-learn ==1.2.2
Requires-Dist: matplotlib ==3.7.1
Requires-Dist: tabulate ==0.9.0
Requires-Dist: numpy ==1.24.3
Requires-Dist: pytest ==7.4.0
Requires-Dist: pandas ==2.0.3
